KSULasso_Python-0.3.data/scripts/KSULasso
sample/RandomLasso.py
sample/__init__.py
sample/test.py
KSULasso_Python-0.3.dist-info/LICENSE
KSULasso_Python-0.3.dist-info/METADATA
KSULasso_Python-0.3.dist-info/WHEEL
KSULasso_Python-0.3.dist-info/top_level.txt
KSULasso_Python-0.3.dist-info/RECORD
