Metadata-Version: 2.1
Name: KSULasso-Python
Version: 0.3
Summary: Lasso Algorithm
Home-page: https://github.com/samskhan/KSULasso
Author: Sams Khan
Author-email: ssamskhann@gmail.com
License: UNKNOWN
Platform: UNKNOWN
Classifier: Programming Language :: Python :: 3
Classifier: License :: OSI Approved :: MIT License
Classifier: Operating System :: OS Independent
